<?xml version="1.0" encoding="utf-8" ?>
<dwsync>
<file name="background.png" server="sftp.itd.umich.edu//afs/umich.edu/group/b/backsdru/Public/html/" local="131450348490000000" remote="131450348490000000" Dst="1" />
<file name="collection.png" server="sftp.itd.umich.edu//afs/umich.edu/group/b/backsdru/Public/html/" local="131450348490000000" remote="131450348490000000" Dst="1" />
<file name="collection_hover.png" server="sftp.itd.umich.edu//afs/umich.edu/group/b/backsdru/Public/html/" local="131450348490000000" remote="131450348490000000" Dst="1" />
<file name="copy.png" server="sftp.itd.umich.edu//afs/umich.edu/group/b/backsdru/Public/html/" local="131450348490000000" remote="131450348490000000" Dst="1" />
<file name="copy_hover.png" server="sftp.itd.umich.edu//afs/umich.edu/group/b/backsdru/Public/html/" local="131450348490000000" remote="131450348490000000" Dst="1" />
<file name="csv.png" server="sftp.itd.umich.edu//afs/umich.edu/group/b/backsdru/Public/html/" local="131450348490000000" remote="131450348490000000" Dst="1" />
<file name="csv_hover.png" server="sftp.itd.umich.edu//afs/umich.edu/group/b/backsdru/Public/html/" local="131450348490000000" remote="131450348490000000" Dst="1" />
<file name="pdf.png" server="sftp.itd.umich.edu//afs/umich.edu/group/b/backsdru/Public/html/" local="131450348490000000" remote="131450348490000000" Dst="1" />
<file name="pdf_hover.png" server="sftp.itd.umich.edu//afs/umich.edu/group/b/backsdru/Public/html/" local="131450348490000000" remote="131450348490000000" Dst="1" />
<file name="print.png" server="sftp.itd.umich.edu//afs/umich.edu/group/b/backsdru/Public/html/" local="131450348490000000" remote="131450348490000000" Dst="1" />
<file name="print_hover.png" server="sftp.itd.umich.edu//afs/umich.edu/group/b/backsdru/Public/html/" local="131450348490000000" remote="131450348490000000" Dst="1" />
<file name="xls.png" server="sftp.itd.umich.edu//afs/umich.edu/group/b/backsdru/Public/html/" local="131450348500000000" remote="131450348500000000" Dst="1" />
<file name="xls_hover.png" server="sftp.itd.umich.edu//afs/umich.edu/group/b/backsdru/Public/html/" local="131450348500000000" remote="131450348500000000" Dst="1" />
</dwsync>